[{"s": "vstroennyj-kholodilnik-kak-delaetsya", "t": "Встроенный холодильник: устройство, монтаж и секреты производства", "i": "⚙️", "c": "ustrojstvo-i-detali"}, {"s": "vse-produkty-kotorye-dolzhny-byt-v-kholodilnike", "t": "Список продуктов для холодильника: что должно быть всегда под рукой", "i": "📅", "c": "sroki-khraneniya"}, {"s": "vstraivaemyj-kholodilnik-kak-razmorazhivat", "t": "Как размораживать встраиваемый холодильник: пошаговая инструкция", "i": "💧", "c": "razmorozka"}, {"s": "vstroennyj-kholodilnik-elektrolyuks-kak-razmorozit", "t": "Как разморозить встроенный холодильник Electrolux: пошаговая инструкция", "i": "💧", "c": "razmorozka"}, {"s": "vstraivaemye-kholodilniki-chem-otlichayutsya-ot-obychnykh", "t": "Встраиваемые холодильники: 7 ключевых отличий от обычных моделей", "i": "🛒", "c": "vybor-kholodilnika"}, {"s": "vstraivaemyj-kholodilnik-chto-znachit", "t": "Встраиваемый холодильник — что это значит и как выбрать", "i": "🛒", "c": "vybor-kholodilnika"}, {"s": "vstroennye-kholodilniki-kak-vyglyadyat", "t": "Встроенные холодильники: фото, виды и особенности дизайна 2026", "i": "🛒", "c": "vybor-kholodilnika"}, {"s": "vstroennyj-kholodilnik-kak-otkryvaetsya", "t": "Как открыть встроенный холодильник: механизмы и секреты", "i": "🛠️", "c": "remont-svoimi-rukami"}, {"s": "vstraivaemyj-kholodilnik-skolko-mesta-zanimaet", "t": "Встраиваемый холодильник: сколько места занимает в кухне", "i": "🔌", "c": "ustanovka-i-montazh"}, {"s": "vstroennyj-kholodilnik-kakoj-firmy-vybrat", "t": "Встроенный холодильник 2026: какой фирмы выбрать для кухни", "i": "🛒", "c": "vybor-kholodilnika"}, {"s": "vstraivaemyj-kholodilnik-krona-zelle-kak", "t": "Встраиваемый холодильник Krona Zelle: монтаж, настройка и уход", "i": "🔌", "c": "ustanovka-i-montazh"}, {"s": "vstraivaemyj-kholodilnik-kakoj-luchshe-vybrat-dlya-doma", "t": "Встраиваемый холодильник 2026: как выбрать лучший для дома", "i": "🛒", "c": "vybor-kholodilnika"}, {"s": "vstavka-drenazhnaya-dlya-kholodilnika-dlya-chego-biryusa", "t": "Дренажная вставка для холодильника Бирюса: назначение и замена", "i": "⚙️", "c": "ustrojstvo-i-detali"}, {"s": "vstraivaemyj-kholodilnik-na-chto-obratit-vnimanie", "t": "Встраиваемый холодильник: 10 ключевых моментов при выборе", "i": "🛒", "c": "vybor-kholodilnika"}, {"s": "vstraivaemyj-kholodilnik-kakoj-marki-luchshe", "t": "Встраиваемый холодильник какой марки лучше: рейтинг 2026", "i": "🛒", "c": "vybor-kholodilnika"}, {"s": "vstraivaemyj-kholodilnik-kak-okhlazhdaetsya", "t": "Как охлаждается встраиваемый холодильник: устройство и принцип работы", "i": "⚙️", "c": "ustrojstvo-i-detali"}, {"s": "vstraivaemye-kholodilniki-kak-ustanovit", "t": "Встраиваемые холодильники: как установить своими руками пошагово", "i": "🔌", "c": "ustanovka-i-montazh"}, {"s": "vstroennyj-kholodilnik-kak-otkryvaetsya-dver", "t": "Как открыть встроенный холодильник: способы и советы", "i": "🛠️", "c": "remont-svoimi-rukami"}, {"s": "vstraivaemyj-kholodilnik-liebherr-v-chem-otlichie", "t": "Встраиваемый холодильник Liebherr: в чем отличие от обычных моделей?", "i": "🛒", "c": "vybor-kholodilnika"}, {"s": "vstroennye-kholodilniki-kak-ustanovit", "t": "Как установить встроенный холодильник: пошаговая инструкция", "i": "🔌", "c": "ustanovka-i-montazh"}, {"s": "vstroennyj-kholodilnik-kak-vytashchit-iz-mebeli", "t": "Как вытащить встроенный холодильник из мебели: пошаговая инструкция", "i": "🔌", "c": "ustanovka-i-montazh"}, {"s": "vstroennyj-kholodilnik-gde-rozetka", "t": "Где розетка для встроенного холодильника: схемы и монтаж", "i": "🔌", "c": "ustanovka-i-montazh"}, {"s": "vstavka-drenazhnaya-dlya-kholodilnika-biryusa-dlya-chego-ona-nuzhna", "t": "Вставка дренажная для холодильника Бирюса: функции и замена", "i": "⚙️", "c": "ustrojstvo-i-detali"}, {"s": "vstroennyj-kholodilnik-kak-podklyuchit-k-rozetke", "t": "Как подключить встроенный холодильник к розетке: инструкция", "i": "🔌", "c": "ustanovka-i-montazh"}, {"s": "vstraivaemyj-ili-obychnyj-kholodilnik-chto-luchshe", "t": "Встраиваемый или обычный холодильник: что лучше выбрать", "i": "🛒", "c": "vybor-kholodilnika"}, {"s": "vstraivaemye-kholodilniki-kakie-byvayut-razmery", "t": "Размеры встраиваемых холодильников: таблица стандартов и ниш", "i": "🛒", "c": "vybor-kholodilnika"}, {"s": "vstroennyj-kholodilnik-gde-delat-rozetku", "t": "Встроенный холодильник где делать розетку: схемы и правила", "i": "🔌", "c": "ustanovka-i-montazh"}, {"s": "vstroennyj-kholodilnik-kak-navesit-fasad", "t": "Как навесить фасад на встроенный холодильник: пошаговая инструкция", "i": "🔌", "c": "ustanovka-i-montazh"}, {"s": "vstroennyj-kholodilnik-kakie-razmery-byvayut", "t": "Встроенный холодильник: стандартные размеры ниши и корпуса", "i": "🛒", "c": "vybor-kholodilnika"}, {"s": "vstraivaemyj-kholodilnik-atlant-kak-razmorozit", "t": "Как разморозить встраиваемый холодильник Атлант: инструкция", "i": "💧", "c": "razmorozka"}, {"s": "vstroennyj-kholodilnik-kak-delayut", "t": "Как делают встроенные холодильники: этапы производства", "i": "⚙️", "c": "ustrojstvo-i-detali"}, {"s": "vstraivaemyj-ili-otdelnostoyashchij-kholodilnik-chto-luchshe", "t": "Встраиваемый или отдельностоящий холодильник: что выбрать?", "i": "🛒", "c": "vybor-kholodilnika"}, {"s": "vstraivaemye-kholodilniki-kakoj-luchshe", "t": "Встраиваемые холодильники: какой лучше выбрать в 2026 году?", "i": "🛒", "c": "vybor-kholodilnika"}, {"s": "vstroennyj-kholodilnik-kak-rabotaet", "t": "Как работает встроенный холодильник: устройство и принцип работы", "i": "⚙️", "c": "ustrojstvo-i-detali"}, {"s": "vstroennyj-kholodilnik-kak-ustanovit-v-shkaf", "t": "Встроенный холодильник как установить в шкаф: пошаговая инструкция", "i": "🔌", "c": "ustanovka-i-montazh"}, {"s": "vstraivaemyj-kholodilnik-hansa-kak-nastroit-temperaturu", "t": "Как настроить температуру в холодильнике Hansa: инструкция", "i": "🌡️", "c": "nastrojka-temperatury"}, {"s": "vstroennyj-kholodilnik-kakoj-luchshe", "t": "Встроенный холодильник какой лучше: гид по выбору 2026", "i": "🛒", "c": "vybor-kholodilnika"}, {"s": "vstavka-drenazhnaya-dlya-kholodilnika-dlya-chego-biryusa-118", "t": "Дренажная вставка для холодильника Бирюса 118: назначение", "i": "⚙️", "c": "ustrojstvo-i-detali"}, {"s": "vstavka-drenazhnaya-dlya-kholodilnika-dlya-chego", "t": "Вставка дренажная для холодильника: зачем нужна, чистка и ремонт", "i": "⚙️", "c": "ustrojstvo-i-detali"}, {"s": "vstraivaemye-kholodilniki-v-chem-otlichie-ot-obychnykh", "t": "Встраиваемые холодильники: отличие от обычных и нюансы монтажа", "i": "🛒", "c": "vybor-kholodilnika"}, {"s": "vstraivaemyj-kholodilnik-kak-vybrat-pravilno", "t": "Как выбрать встраиваемый холодильник: полное руководство", "i": "🛒", "c": "vybor-kholodilnika"}, {"s": "vstroennyj-kholodilnik-kakie-razmery-byvayut-v-kukhonnyj-garnitur", "t": "Размеры встраиваемых холодильников: стандарты и габариты ниш", "i": "🛒", "c": "vybor-kholodilnika"}, {"s": "vstraivaemyj-kholodilnik-kak-ustanovit-na-kukhne", "t": "Как установить встраиваемый холодильник на кухне: пошаговая инструкция", "i": "🔌", "c": "ustanovka-i-montazh"}, {"s": "vstroennyj-kholodilnik-kak-krepit-fasad", "t": "Как крепить фасад на встроенный холодильник: пошаговая инструкция", "i": "📁", "c": null}, {"s": "vstroennyj-kholodilnik-kak-vstraivaetsya", "t": "Как встраивается встроенный холодильник: пошаговая инструкция", "i": "🔌", "c": "ustanovka-i-montazh"}, {"s": "vse-chto-bylo-v-kholodilnike", "t": "Все что было в холодильнике: сроки, хранение и безопасность", "i": "📅", "c": "sroki-khraneniya"}, {"s": "vse-protukhlo-v-kholodilnike-kak-izbavitsya-ot-zapakha", "t": "В холодильнике все протухло: как быстро избавиться от запаха", "i": "🧼", "c": "ukhod-i-chistka"}, {"s": "vstraivaemyj-kholodilnik-kak-ustanovit-fasady", "t": "Как установить фасады на встраиваемый холодильник: пошаговая инструкция", "i": "🔌", "c": "ustanovka-i-montazh"}, {"s": "vse-chto-v-kholodilnike-tozhe-moe-video", "t": "Все, что в холодильнике, тоже мое: видео-разбор и сроки хранения", "i": "📅", "c": "sroki-khraneniya"}, {"s": "vstroennyj-kholodilnik-v-kukhonnyj-garnitur-eto-kak", "t": "Встроенный холодильник в гарнитур: монтаж и нюансы", "i": "🔌", "c": "ustanovka-i-montazh"}, {"s": "vstroennye-kholodilniki-kakie-luchshe", "t": "Встроенные холодильники: какие лучше выбрать в 2026 году", "i": "🛒", "c": "vybor-kholodilnika"}, {"s": "vstavka-drenazhnaya-v-kholodilnike-dlya-chego", "t": "Вставка дренажная в холодильнике: для чего нужна и как чистить", "i": "🧼", "c": "ukhod-i-chistka"}, {"s": "vstavka-drenazhnaya-dlya-kholodilnika-dlya-chego-biryusa-151", "t": "Дренажная вставка для холодильника Бирюса 151: назначение", "i": "⚙️", "c": "ustrojstvo-i-detali"}, {"s": "vstraivaemye-kholodilniki-kakoj-vybrat-rejting", "t": "Встраиваемые холодильники: какой выбрать и рейтинг лучших", "i": "🛒", "c": "vybor-kholodilnika"}, {"s": "vstroennyj-kholodilnik-kakoj-vysoty-byvaet", "t": "Высота встроенных холодильников: стандарты, размеры и ниши", "i": "🛒", "c": "vybor-kholodilnika"}, {"s": "vse-chto-est-v-kholodilnike", "t": "Что приготовить из продуктов в холодильнике: рецепты и идеи", "i": "📁", "c": null}, {"s": "vstroennyj-kholodilnik-kak-smotritsya", "t": "Встроенный холодильник как смотрится: фото, дизайн и ошибки", "i": "🛒", "c": "vybor-kholodilnika"}, {"s": "vstraivaemyj-kholodilnik-eto-kak", "t": "Встраиваемый холодильник это как: устройство, монтаж и выбор", "i": "🔌", "c": "ustanovka-i-montazh"}, {"s": "vstroennyj-kholodilnik-kak-okhlazhdaetsya", "t": "Как охлаждается встроенный холодильник: устройство и принцип", "i": "⚙️", "c": "ustrojstvo-i-detali"}, {"s": "vstroennyj-kholodilnik-u-steny-skolko-otstupit", "t": "Отступ встроенного холодильника от стены: нормы вентиляции", "i": "🔌", "c": "ustanovka-i-montazh"}, {"s": "vstroennye-kholodilniki-razmery-kakie-byvayut", "t": "Размеры встроенных холодильников: стандарты, ниши и габариты", "i": "🛒", "c": "vybor-kholodilnika"}, {"s": "vstroennyj-kholodilnik-liebherr-kak-razmorazhivat", "t": "Встроенный холодильник Liebherr: как размораживать правильно", "i": "💧", "c": "razmorozka"}, {"s": "vstraivaemyj-kholodilnik-v-chem-raznitsa-mezhdu-obychnym", "t": "Встраиваемый холодильник: в чем разница с обычным? Сравнение", "i": "🛒", "c": "vybor-kholodilnika"}, {"s": "vstroennye-kholodilniki-kakoj-luchshe", "t": "Встроенные холодильники: какой лучше выбрать для кухни", "i": "🛒", "c": "vybor-kholodilnika"}, {"s": "vstraivaemyj-kholodilnik-kakoj-kupit-luchshe", "t": "Какой встраиваемый холодильник лучше: советы эксперта", "i": "🛒", "c": "vybor-kholodilnika"}, {"s": "vstroennyj-kholodilnik-kak-eto", "t": "Встроенный холодильник: как это работает, плюсы и минусы", "i": "🛒", "c": "vybor-kholodilnika"}, {"s": "vstroennyj-kholodilnik-kak-vyglyadit-bez-fasada", "t": "Встроенный холодильник без фасада: как выглядит и устройство", "i": "🔌", "c": "ustanovka-i-montazh"}, {"s": "vstraivaemyj-kholodilnik-na-chto-obratit-vnimanie-pri-pokupke", "t": "Встраиваемый холодильник: на что обратить внимание при покупке", "i": "🛒", "c": "vybor-kholodilnika"}, {"s": "vstraivaemyj-kholodilnik-kak-krepit-dvertsu", "t": "Как крепить дверцу встраиваемого холодильника: пошаговая инструкция", "i": "🔌", "c": "ustanovka-i-montazh"}, {"s": "vstraivaemye-kholodilniki-kakie-luchshe", "t": "Встраиваемые холодильники: какие лучше выбрать в 2026 году", "i": "🛒", "c": "vybor-kholodilnika"}, {"s": "vstraivaemyj-kholodilnik-kakoj-firmy-luchshe", "t": "Встраиваемый холодильник какой фирмы лучше: рейтинг и советы", "i": "🛒", "c": "vybor-kholodilnika"}, {"s": "vstraivaemye-kholodilniki-otzyvy-kakoj-luchshe", "t": "Встраиваемые холодильники: отзывы экспертов, какой лучше выбрать", "i": "🛒", "c": "vybor-kholodilnika"}, {"s": "vstraivaemyj-kholodilnik-atlant-kak-ustanovit", "t": "Встраиваемый холодильник Атлант: пошаговая инструкция по установке", "i": "🔌", "c": "ustanovka-i-montazh"}, {"s": "vse-chto-est-v-kholodilnike-retsepty", "t": "Что приготовить из продуктов в холодильнике: быстрые рецепты", "i": "📅", "c": "sroki-khraneniya"}]